territories_dashboard_lib/__init__.py
territories_dashboard_lib/commons/__init__.py
territories_dashboard_lib/commons/decorators.py
territories_dashboard_lib/commons/models.py
territories_dashboard_lib/commons/types.py
territories_dashboard_lib/geo_lib/__init__.py
territories_dashboard_lib/geo_lib/admin.py
territories_dashboard_lib/geo_lib/enums.py
territories_dashboard_lib/geo_lib/logic.py
territories_dashboard_lib/geo_lib/models.py
territories_dashboard_lib/geo_lib/payloads.py
territories_dashboard_lib/geo_lib/urls.py
territories_dashboard_lib/geo_lib/views.py
territories_dashboard_lib/geo_lib/migrations/0001_initial.py
territories_dashboard_lib/geo_lib/migrations/0002_geoelement_linked_to_indicator.py
territories_dashboard_lib/geo_lib/migrations/0003_geofeature_color_column_geofeature_size_column.py
territories_dashboard_lib/geo_lib/migrations/0004_geofeature_legend.py
territories_dashboard_lib/geo_lib/migrations/__init__.py
territories_dashboard_lib/indicators_lib/__init__.py
territories_dashboard_lib/indicators_lib/admin.py
territories_dashboard_lib/indicators_lib/enums.py
territories_dashboard_lib/indicators_lib/export.py
territories_dashboard_lib/indicators_lib/format.py
territories_dashboard_lib/indicators_lib/methodo_pdf.py
territories_dashboard_lib/indicators_lib/models.py
territories_dashboard_lib/indicators_lib/payloads.py
territories_dashboard_lib/indicators_lib/refresh_filters.py
territories_dashboard_lib/indicators_lib/table.py
territories_dashboard_lib/indicators_lib/urls.py
territories_dashboard_lib/indicators_lib/utils.py
territories_dashboard_lib/indicators_lib/views.py
territories_dashboard_lib/indicators_lib/migrations/0001_initial.py
territories_dashboard_lib/indicators_lib/migrations/0002_filter_color_indicator_min_mesh_and_more.py
territories_dashboard_lib/indicators_lib/migrations/0003_indicator_short_title.py
territories_dashboard_lib/indicators_lib/migrations/0004_alter_indicator_min_mesh.py
territories_dashboard_lib-1.2.0.dist-info/licenses/licence.md
territories_dashboard_lib-1.2.0.dist-info/METADATA
territories_dashboard_lib-1.2.0.dist-info/WHEEL
territories_dashboard_lib-1.2.0.dist-info/top_level.txt
territories_dashboard_lib-1.2.0.dist-info/RECORD
