Metadata-Version: 2.4
Name: territories-dashboard-lib
Version: 1.2.0
Summary: Librairie pour la visualisation d'indicateurs territoriaux.
Author-email: Bastien <bastien@prune.sh>
Classifier: Programming Language :: Python :: 3
Classifier: Operating System :: OS Independent
Classifier: Development Status :: 3 - Alpha
Classifier: Intended Audience :: Developers
Classifier: Topic :: Software Development :: Libraries
Requires-Python: <3.14,>=3.13
License-File: licence.md
Requires-Dist: django<6
Requires-Dist: django-nested-admin>=4.1.1
Requires-Dist: geoip2>=5.1.0
Requires-Dist: gunicorn>=23.0.0
Requires-Dist: ipython>=8.32.0
Requires-Dist: martor>=1.7.15
Requires-Dist: pre-commit>=4.2.0
Requires-Dist: psycopg2-binary>=2.9.10
Requires-Dist: pydantic>=2.10.6
Requires-Dist: pydantic-settings>=2.7.1
Requires-Dist: whitenoise>=6.9.0
Dynamic: license-file
